oca_port/__init__.py
oca_port/app.py
oca_port/exceptions.py
oca_port/migrate_addon.py
oca_port/port_addon_pr.py
oca_port/cli/__init__.py
oca_port/cli/main.py
oca_port/cli/pr.py
oca_port/tests/__init__.py
oca_port/tests/common.py
oca_port/tests/test_app.py
oca_port/tests/test_branches_diff.py
oca_port/tests/test_migrate_addon.py
oca_port/tests/test_utils_cache.py
oca_port/tests/test_utils_git.py
oca_port/tests/test_utils_github.py
oca_port/tests/test_utils_misc.py
oca_port/tests/test_utils_session.py
oca_port/tests/data/manifest.py
oca_port/utils/__init__.py
oca_port/utils/cache.py
oca_port/utils/git.py
oca_port/utils/github.py
oca_port/utils/misc.py
oca_port/utils/session.py
oca_port/utils/storage.py
oca_port-0.19.dist-info/licenses/LICENSE
oca_port-0.19.dist-info/METADATA
oca_port-0.19.dist-info/WHEEL
oca_port-0.19.dist-info/entry_points.txt
oca_port-0.19.dist-info/top_level.txt
oca_port-0.19.dist-info/RECORD
