Metadata-Version: 2.4
Name: oca_port
Version: 0.19
Summary: OCA tool to help with modules migration
Author: Odoo Community Association (OCA)
Author-email: Sébastien Alix <sebastien.alix@camptocamp.com>, Simone Orsi <simone.orsi@camptocamp.com>
License:                    GNU LESSER GENERAL PUBLIC LICENSE
Project-URL: homepage, https://github.com/OCA/oca-port
Project-URL: documentation, https://github.com/OCA/oca-port
Project-URL: repository, https://github.com/OCA/oca-port
Keywords: odoo,oca,port,migration,modules,addons
Classifier: License :: OSI Approved :: GNU Lesser General Public License v3 (LGPLv3)
Classifier: Programming Language :: Python :: 3
Classifier: Framework :: Odoo
Requires-Python: >=3.8
License-File: LICENSE
Requires-Dist: click
Requires-Dist: gitpython
Requires-Dist: requests
Requires-Dist: giturlparse
Requires-Dist: git-filter-repo
Provides-Extra: test
Requires-Dist: pytest; extra == "test"
Requires-Dist: coverage; extra == "test"
Dynamic: license-file
